[
  {
    "id": "1",
    "manufacturer": "Honda",
    "model": "Toyota Avanza",
    "modelCode": "RX",
    "year": "2016",
    "price": 50,
    "engine": "2.3K CC",
    "transmission": "Manual",
    "fuelType": "Petrol",
    "mileage": "25K KM",
    "image": "/images/cars/best-01.jpg"
  },
  {
    "id": "2",
    "manufacturer": "Honda",
    "model": "Chevrolet",
    "modelCode": "GTR",
    "year": "2017",
   "price": 50,
    "engine": "2.3K CC",
    "transmission": "Manual",
    "fuelType": "Petrol",
    "mileage": "25K KM",
    "image": "/images/cars/best-02.jpg"
  },
  {
    "id": "3",
    "manufacturer": "Mercedes Benz",
    "model": "Volkswagen",
    "modelCode": "GTR",
    "year": "2016",
   "price": 50,
    "engine": "2.3K CC",
    "transmission": "Manual",
    "fuelType": "Petrol",
    "mileage": "25K KM",
    "image": "/images/cars/best-03.jpg"
  },
  {
    "id": "4",
    "manufacturer": "Audi",
    "model": "Audi Sport",
    "modelCode": "S8",
    "year": "2024",
   "price": 50,
    "engine": "2.3K CC",
    "transmission": "Manual",
    "fuelType": "Petrol",
    "mileage": "25K KM",
    "image": "/images/cars/best-04.jpg"
  },
  {
    "id": "5",
    "manufacturer": "Ferrari",
    "model": "Bugatti Feyron",
    "modelCode": "F2",
    "year": "2017",
    "price": 50,
    "engine": "2.3K CC",
    "transmission": "Manual",
    "fuelType": "Petrol",
    "mileage": "25K KM",
    "image": "/images/cars/best-05.jpg"
  },
  {
    "id": "6",
    "manufacturer": "Toyota",
    "model": "Mercedes Benz",
    "modelCode": "R3",
    "year": "2016",
    "price": 50,
    "engine": "2.3K CC",
    "transmission": "Manual",
    "fuelType": "Petrol",
    "mileage": "25K KM",
    "image": "/images/cars/best-06.jpg"
  },
  {
    "id": "7",
    "manufacturer": "Volkswagen",
    "model": "Golf GTI",
    "modelCode": "VW7",
    "year": "2018",
    "price": 65,
    "engine": "2.0K CC",
    "transmission": "Automatic",
    "fuelType": "Diesel",
    "mileage": "35K KM",
    "image": "/images/cars/best-01.jpg"
  },
  {
    "id": "8",
    "manufacturer": "Audi",
    "model": "RS6 Avant",
    "modelCode": "A8",
    "year": "2020",
    "price": 120,
    "engine": "4.0K CC",
    "transmission": "Automatic",
    "fuelType": "Petrol",
    "mileage": "20K KM",
    "image": "/images/cars/best-02.jpg"
  },
  {
    "id": "9",
    "manufacturer": "Ferrari",
    "model": "488 GTB",
    "modelCode": "F9",
    "year": "2019",
    "price": 250,
    "engine": "3.9K CC",
    "transmission": "Automatic",
    "fuelType": "Petrol",
    "mileage": "15K KM",
    "image": "/images/cars/best-03.jpg"
  }

]
